{
  "skillId": "tanstack-virtual",
  "source": "tanstack-skills/tanstack-skills",
  "owner": "tanstack-skills",
  "repo": "tanstack-skills",
  "resolved_from": "skills.json",
  "origin": {
    "source": "tanstack-skills/tanstack-skills",
    "skillId": "tanstack-virtual",
    "name": "tanstack-virtual",
    "installs": 1466,
    "owner": "tanstack-skills",
    "repo": "tanstack-skills",
    "githubUrl": "https://github.com/tanstack-skills/tanstack-skills",
    "displayName": "Tanstack Virtual"
  }
}