{
  "skillId": "foldseek-structural-search",
  "source": "google-deepmind/science-skills",
  "owner": "google-deepmind",
  "repo": "science-skills",
  "resolved_from": "skills.json",
  "origin": {
    "source": "google-deepmind/science-skills",
    "skillId": "foldseek-structural-search",
    "name": "foldseek-structural-search",
    "installs": 963,
    "owner": "google-deepmind",
    "repo": "science-skills",
    "githubUrl": "https://github.com/google-deepmind/science-skills",
    "displayName": "Foldseek Structural Search"
  }
}